{"ongoing_trials": {}, "hyperparameters": {"space": [{"class_name": "Int", "config": {"name": "units", "default": null, "conditions": [], "min_value": 32, "max_value": 512, "step": 32, "sampling": "linear"}}, {"class_name": "Int", "config": {"name": "num_layers", "default": null, "conditions": [], "min_value": 1, "max_value": 3, "step": 1, "sampling": "linear"}}, {"class_name": "Int", "config": {"name": "units_0", "default": null, "conditions": [], "min_value": 32, "max_value": 512, "step": 32, "sampling": "linear"}}, {"class_name": "Choice", "config": {"name": "learning_rate", "default": 0.01, "conditions": [], "values": [0.01, 0.001, 0.0001], "ordered": true}}, {"class_name": "Int", "config": {"name": "units_1", "default": null, "conditions": [], "min_value": 32, "max_value": 512, "step": 32, "sampling": "linear"}}, {"class_name": "Int", "config": {"name": "units_2", "default": null, "conditions": [], "min_value": 32, "max_value": 512, "step": 32, "sampling": "linear"}}], "values": {"units": 32, "num_layers": 1, "units_0": 32, "learning_rate": 0.01, "units_1": 32, "units_2": 32}}, "start_order": ["00", "01", "02", "03", "04", "05", "06", "07", "08", "09"], "end_order": ["00", "01", "02", "03", "04", "05", "06", "07", "08", "09"], "run_times": {"00": 1, "01": 1, "02": 1, "03": 1, "04": 1, "05": 1, "06": 1, "07": 1, "08": 1, "09": 1}, "retry_queue": [], "seed": 5690, "seed_state": 5742, "tried_so_far": ["f7af59130669216b1c1e81607862b044", "69f1a8c8cc4266c2f9e1ee66a5e9a9d8", "eb8c71d709e2508632d3a375295136aa", "3dde8cab0bce2b970801b1ac9f050a64", "28d530d165ba980555452e9cbf43010b", "f097813f54fc6008fb12a997a5985c48", "139f8c0de720ba2cb8a35938e73b4fcd", "7813c849d61b7a35fc42c67638cbe744", "4c7d39378d6eb4aed8c1a8c75dbb52ff", "fdd0edd3d7f487a763b119099ac392a2"], "id_to_hash": {"00": "7813c849d61b7a35fc42c67638cbe744", "01": "139f8c0de720ba2cb8a35938e73b4fcd", "02": "28d530d165ba980555452e9cbf43010b", "03": "69f1a8c8cc4266c2f9e1ee66a5e9a9d8", "04": "eb8c71d709e2508632d3a375295136aa", "05": "fdd0edd3d7f487a763b119099ac392a2", "06": "3dde8cab0bce2b970801b1ac9f050a64", "07": "4c7d39378d6eb4aed8c1a8c75dbb52ff", "08": "f097813f54fc6008fb12a997a5985c48", "09": "f7af59130669216b1c1e81607862b044"}, "display": {"search_start": "2025-05-28T13:05:56.736429", "trial_start": {"00": "2025-05-28T13:05:56.736429", "01": "2025-05-28T13:06:05.483252", "02": "2025-05-28T13:06:12.251728", "03": "2025-05-28T13:06:19.257178", "04": "2025-05-28T13:06:26.459845", "05": "2025-05-28T13:06:33.367241", "06": "2025-05-28T13:06:41.616462", "07": "2025-05-28T13:06:48.956923", "08": "2025-05-28T13:06:56.514942", "09": "2025-05-28T13:07:02.323403"}, "trial_number": {"00": 1, "01": 2, "02": 3, "03": 4, "04": 5, "05": 6, "06": 7, "07": 8, "08": 9, "09": 10}}}